<annotation>
	<folder>images</folder>
	<filename>1041.jpg</filename>
	<path>F:\hanzishibie\images\1041.jpg</path>
	<source>
		<database>Unknown</database>
	</source>
	<size>
		<width>320</width>
		<height>160</height>
		<depth>3</depth>
	</size>
	<segmented>0</segmented>
	<object>
		<name>飞</name>
		<pose>Unspecified</pose>
		<truncated>0</truncated>
		<difficult>0</difficult>
		<bndbox>
			<xmin>30</xmin>
			<ymin>37</ymin>
			<xmax>58</xmax>
			<ymax>72</ymax>
		</bndbox>
	</object>
	<object>
		<name>翼</name>
		<pose>Unspecified</pose>
		<truncated>0</truncated>
		<difficult>0</difficult>
		<bndbox>
			<xmin>96</xmin>
			<ymin>53</ymin>
			<xmax>124</xmax>
			<ymax>87</ymax>
		</bndbox>
	</object>
	<object>
		<name>齐</name>
		<pose>Unspecified</pose>
		<truncated>0</truncated>
		<difficult>0</difficult>
		<bndbox>
			<xmin>195</xmin>
			<ymin>76</ymin>
			<xmax>228</xmax>
			<ymax>110</ymax>
		</bndbox>
	</object>
	<object>
		<name>比</name>
		<pose>Unspecified</pose>
		<truncated>0</truncated>
		<difficult>0</difficult>
		<bndbox>
			<xmin>118</xmin>
			<ymin>99</ymin>
			<xmax>152</xmax>
			<ymax>135</ymax>
		</bndbox>
	</object>
</annotation>
