<annotation>
	<folder>images</folder>
	<filename>26.jpg</filename>
	<path>F:\hanzishibie\images\26.jpg</path>
	<source>
		<database>Unknown</database>
	</source>
	<size>
		<width>320</width>
		<height>160</height>
		<depth>3</depth>
	</size>
	<segmented>0</segmented>
	<object>
		<name>人</name>
		<pose>Unspecified</pose>
		<truncated>0</truncated>
		<difficult>0</difficult>
		<bndbox>
			<xmin>232</xmin>
			<ymin>80</ymin>
			<xmax>261</xmax>
			<ymax>111</ymax>
		</bndbox>
	</object>
	<object>
		<name>生</name>
		<pose>Unspecified</pose>
		<truncated>0</truncated>
		<difficult>0</difficult>
		<bndbox>
			<xmin>173</xmin>
			<ymin>73</ymin>
			<xmax>208</xmax>
			<ymax>108</ymax>
		</bndbox>
	</object>
	<object>
		<name>不</name>
		<pose>Unspecified</pose>
		<truncated>0</truncated>
		<difficult>0</difficult>
		<bndbox>
			<xmin>45</xmin>
			<ymin>46</ymin>
			<xmax>75</xmax>
			<ymax>73</ymax>
		</bndbox>
	</object>
	<object>
		<name>满</name>
		<pose>Unspecified</pose>
		<truncated>0</truncated>
		<difficult>0</difficult>
		<bndbox>
			<xmin>114</xmin>
			<ymin>85</ymin>
			<xmax>152</xmax>
			<ymax>121</ymax>
		</bndbox>
	</object>
	<object>
		<name>百</name>
		<pose>Unspecified</pose>
		<truncated>0</truncated>
		<difficult>0</difficult>
		<bndbox>
			<xmin>28</xmin>
			<ymin>103</ymin>
			<xmax>61</xmax>
			<ymax>132</ymax>
		</bndbox>
	</object>
</annotation>
